MANIFEST.in
README.txt
setup.py
docs/HISTORY.txt
src/zeam/__init__.py
src/zeam.form.ztk.egg-info/PKG-INFO
src/zeam.form.ztk.egg-info/SOURCES.txt
src/zeam.form.ztk.egg-info/dependency_links.txt
src/zeam.form.ztk.egg-info/entry_points.txt
src/zeam.form.ztk.egg-info/namespace_packages.txt
src/zeam.form.ztk.egg-info/not-zip-safe
src/zeam.form.ztk.egg-info/requires.txt
src/zeam.form.ztk.egg-info/top_level.txt
src/zeam/form/__init__.py
src/zeam/form/ztk/__init__.py
src/zeam/form/ztk/actions.py
src/zeam/form/ztk/compat.py
src/zeam/form/ztk/configure.zcml
src/zeam/form/ztk/customizations.py
src/zeam/form/ztk/datamanager.py
src/zeam/form/ztk/fields.py
src/zeam/form/ztk/ftesting.zcml
src/zeam/form/ztk/interfaces.py
src/zeam/form/ztk/testing.py
src/zeam/form/ztk/validation.py
src/zeam/form/ztk/ftests/__init__.py
src/zeam/form/ztk/ftests/test_ztk.py
src/zeam/form/ztk/ftests/forms/__init__.py
src/zeam/form/ztk/ftests/forms/editform.py
src/zeam/form/ztk/ftests/forms/editform_fixture.py
src/zeam/form/ztk/ftests/forms/ztkform.py
src/zeam/form/ztk/ftests/forms/ztkform_fixture.py
src/zeam/form/ztk/tests/__init__.py
src/zeam/form/ztk/tests/fields.txt
src/zeam/form/ztk/tests/test_doctest.py
src/zeam/form/ztk/tests/validation.txt
src/zeam/form/ztk/widgets/__init__.py
src/zeam/form/ztk/widgets/bool.py
src/zeam/form/ztk/widgets/choice.py
src/zeam/form/ztk/widgets/collection.py
src/zeam/form/ztk/widgets/date.py
src/zeam/form/ztk/widgets/email.py
src/zeam/form/ztk/widgets/link.py
src/zeam/form/ztk/widgets/number.py
src/zeam/form/ztk/widgets/object.py
src/zeam/form/ztk/widgets/password.py
src/zeam/form/ztk/widgets/text.py
src/zeam/form/ztk/widgets/textline.py
src/zeam/form/ztk/widgets/time.py
src/zeam/form/ztk/widgets/uri.py
src/zeam/form/ztk/widgets/bool_templates/checkboxwidget.cpt
src/zeam/form/ztk/widgets/choice_templates/choicedisplaywidget.cpt
src/zeam/form/ztk/widgets/choice_templates/choicefieldwidget.cpt
src/zeam/form/ztk/widgets/choice_templates/radiofieldwidget.cpt
src/zeam/form/ztk/widgets/collection_templates/listgenericfieldwidget.cpt
src/zeam/form/ztk/widgets/collection_templates/listobjectfieldwidget.cpt
src/zeam/form/ztk/widgets/collection_templates/multichoicedisplayfieldwidget.cpt
src/zeam/form/ztk/widgets/collection_templates/multichoicefieldwidget.cpt
