Metadata-Version: 2.1
Name: zeam.form.ztk
Version: 1.4.0
Summary: Zope Toolkit support for zeam.form
Home-page: http://pypi.python.org/pypi/zeam.form.ztk
Author: Sylvain Viollon
Author-email: thefunny@gmail.com
License: BSD
Keywords: zeam form zope schema edit content
Platform: UNKNOWN
Classifier: Framework :: Zope3
Classifier: Programming Language :: Python
Classifier: Programming Language :: Zope
Classifier: Intended Audience :: Developers
Classifier: Topic :: Software Development :: Libraries :: Python Modules
Provides-Extra: email
Provides-Extra: fanstatic
Provides-Extra: test
